audioshake_job_manager/__init__.py
audioshake_job_manager-0.0.6.dist-info/METADATA
audioshake_job_manager-0.0.6.dist-info/WHEEL
audioshake_job_manager-0.0.6.dist-info/top_level.txt
audioshake_job_manager-0.0.6.dist-info/RECORD
