Metadata-Version: 2.1
Name: audioshake-job-manager
Version: 0.0.6
Summary: AudioShake job manager
Author-email: Sylvester Okonkwo <sylvester@audioshake.ai>
Requires-Python: >=3.9
Requires-Dist: boto3
